generations/__init__.py
generations/base_model.py
generations/biennial.py
generations/buckley.py
generations/create_config.py
generations/default_parameters.cfg
generations/double_agent.py
generations/memoization.py
generations/nicholson_bailey.py
generations/seed_feeder_biennial.py
tests/__init__.py
tests/test_base_model.py
tests/test_biennial.py
tests/test_buckley.py
tests/test_nicholson_bailey.py
generations-1.3.0.dist-info/LICENSE
generations-1.3.0.dist-info/METADATA
generations-1.3.0.dist-info/WHEEL
generations-1.3.0.dist-info/top_level.txt
generations-1.3.0.dist-info/RECORD
