Metadata-Version: 2.1
Name: generations
Version: 1.3.0
Summary: A set of recursive population models for ecologists
Home-page: https://github.com/alfalimajuliett/generations
Author: M. Marek-Spartz
Author-email: patt0335@umn.edu
License: UNKNOWN
Platform: UNKNOWN
Classifier: Programming Language :: Python :: 3
Classifier: Programming Language :: Python :: 2
Classifier: License :: OSI Approved :: MIT License
Classifier: Operating System :: OS Independent
Classifier: Topic :: Scientific/Engineering
Classifier: Topic :: Software Development :: Libraries :: Python Modules
Classifier: Topic :: Utilities
Classifier: Environment :: Console
